{
    "Tool Development Kit": {
        "author": "Ivan Titov",
        "source": "anvdev/Houdini_TDK",
        "source_type": "github",
        "hversion": "17+",
        "hlicense": "commercial"
    },
    "Hammer": {
        "author": "Ivan Titov",
        "source": "anvdev/Hammer-Tools",
        "source_type": "github",
        "hversion": "18.0.425+",
        "hlicense": "commercial",
        "status": "dev"
    },
    "Advanced VEX Library": {
        "author": "Ivan Titov",
        "source": "AdvancedVEXLibrary/Advanced-VEX-Library",
        "source_type": "github",
        "hversion": "16.5+",
        "hlicense": "commercial",
        "status": "dev"
    },
    "HPaste": {
        "author": "Anatolii Iudanov",
        "description": "Simple and fast exchange of node networks through any messenger",
        "source": "pedohorse/hpaste",
        "source_type": "github",
        "hversion": "16+",
        "hlicense": "commercial"
    },
    "Map Zoomer": {
        "author": "Anatolii Iudanov",
        "source": "pedohorse/mapzoomer",
        "source_type": "github",
        "hversion": "16.5+",
        "hlicense": "commercial",
        "status": "prototype"
    },
    "Gear Logic": {
        "author": "Anatolii Iudanov",
        "source": "pedohorse/gearlogic",
        "source_type": "github",
        "hversion": "16.5+",
        "hlicense": "commercial",
        "status": "prototype"
    },
    "MOPs": {
        "visible": false,
        "author": "Henry Foster",
        "source": "toadstorm/MOPS",
        "source_type": "github",
        "hversion": "17+",
        "hlicense": "commercial"
    },
    "qLib": {
        "visible": false,
        "author": "qLab",
        "source": "qLab/qLib",
        "source_type": "github",
        "hversion": "17.5.321+",
        "hlicense": "commercial"
    },
    "PDG Mutagen": {
        "visible": false,
        "author": "Adrian Meyer",
        "source": "MeyerAdrian/pdg_mutagen",
        "source_type": "github",
        "hversion": "17.5+",
        "hlicense": "commercial",
        "status": "prototype",
        "root": "houdini"
    },
    "MRP Mantra Shaders": {
        "visible": false,
        "author": "Main Road Post",
        "source": "MainRoadPost/houdini_configs",
        "source_type": "github",
        "hversion": "16.5+",
        "hlicense": "commercial"
    },
    "Massive Toolkit": {
        "visible": false,
        "author": "Jordi Bares",
        "source": "jordibares/massive-toolkit-for-houdini",
        "source_type": "github"
    },
    "DMNK Tools": {
        "visible": false,
        "author": "Dominik Lingenover",
        "source": "DominikLingenover/DMNK-Tools",
        "source_type": "github",
        "hversion": "17.5+",
        "hlicense": "commercial"
    },
    "Mantra Fog Shader": {
        "visible": false,
        "author": "Alexey Smolenchuk",
        "source": "somesanctus/volumelight",
        "source_type": "github",
        "hversion": "16+",
        "hlicense": "commercial",
        "status": "prototype"
    },
    "PhyShader (Mantra)": {
        "visible": false,
        "author": "Roman Saldygashev",
        "source": "groundflyer/physhader-for-mantra",
        "source_type": "github",
        "hversion": "15.5-15.5",
        "hlicense": "commercial",
        "status": "prototype"
    },
    "qq": {
        "visible": false,
        "author": "Jiri Miratsky",
        "source": "lex-ikoon/qq",
        "source_type": "github",
        "hversion": "16.5+",
        "hlicense": "commercial"
    },
    "siLib": {
        "visible": false,
        "author": "Andy Nicholas",
        "source": "fxnut/siLib",
        "source_type": "github",
        "hversion": "15.5-16.5",
        "hlicense": "commercial",
        "status": "prototype"
    },
    "Deadline farm submission tool": {
        "visible": false,
        "author": "Andy Nicholas",
        "source": "fxnut/hou_farm",
        "source_type": "github",
        "hversion": "16+",
        "hlicense": "commercial"
    }
}
